{
  "meta": {
    "id": "ustv-61f6b2b8-9ee2-4b47-abe6-6818a02d199b",
    "type": "tv",
    "name": "Classic TV Crime Drama",
    "genres": [
      "Entertainment"
    ],
    "poster": "https://upload.wikimedia.org/wikipedia/commons/thumb/8/8f/Pluto_TV_logo.svg/512px-Pluto_TV_logo.svg.png",
    "background": "https://upload.wikimedia.org/wikipedia/commons/thumb/8/8f/Pluto_TV_logo.svg/512px-Pluto_TV_logo.svg.png",
    "logo": "https://upload.wikimedia.org/wikipedia/commons/thumb/8/8f/Pluto_TV_logo.svg/512px-Pluto_TV_logo.svg.png",
    "description": "Classic TV Crime Drama - Entertainment"
  }
}