{
  "streams": [
    {
      "url": "https://wurlrainbowmedia.global.transmit.live/hls/68c49e4709574e8405506cb3/v1/amc_scaresbyshudder_1/lg_us/latest/main/hls/playlist.m3u8?wurl_channel=1566&wurl_name=ScaresbyShudder&coppa=0&uid=[DEVICE_ID]&rdid=[IFA]&ifatype=[IFA_TYPE]&dnt=[LMT]&donotsell=[DNS]&isgdpr=[GDPR]&gdpr=[GDPR_CONSENT]&country=[COUNTRY]&pr=[US_PRIVACY]&appstoreurl=[APP_STOREURL]&bundleid=[APP_BUNDLE]&appname=[APP_NAME]&appversion=[APP_VERSION]&dt=[DEVICE_TYPE]&make=[DEVICE_MAKE]&model=[DEVICE_MODEL]&targetad=[TARGETAD_ALLOWED]&fck=[FCK]&viewsize=[VIEWSIZE]&nonce=[NONCE]",
      "behaviorHints": {
        "notWebReady": true
      },
      "name": "LG",
      "description": "LG"
    }
  ]
}